README.md
setup.py
django_npick/__init__.py
django_npick/admin.py
django_npick/apps.py
django_npick/forms.py
django_npick/models.py
django_npick/views.py
django_npick/widgets.py
django_npick.egg-info/PKG-INFO
django_npick.egg-info/SOURCES.txt
django_npick.egg-info/dependency_links.txt
django_npick.egg-info/top_level.txt
django_npick/migrations/0001_initial.py
django_npick/migrations/__init__.py
django_npick/static/css/icon-picker.css
django_npick/static/css/unicons-icon-picker.css
django_npick/static/js/icon-picker.js
django_npick/static/js/unicons-icon-picker.js
django_npick/templates/admin/change_form.html